LICENSE.txt
MANIFEST.in
README.md
setup.cfg
setup.py
start_flask/__init__.py
start_flask/cli.py
start_flask/project_builder.py
start_flask.egg-info/PKG-INFO
start_flask.egg-info/SOURCES.txt
start_flask.egg-info/dependency_links.txt
start_flask.egg-info/entry_points.txt
start_flask.egg-info/requires.txt
start_flask.egg-info/top_level.txt
start_flask/templates/.env
start_flask/templates/.gitignore
start_flask/templates/.secrets.toml
start_flask/templates/Makefile
start_flask/templates/app.py
start_flask/templates/conftest.py
start_flask/templates/index.html
start_flask/templates/requirements-dev.txt
start_flask/templates/requirements.txt
start_flask/templates/settings.toml
start_flask/templates/setup.py
start_flask/templates/test_app.py
start_flask/templates/ext/admin.py
start_flask/templates/ext/cli.py
start_flask/templates/ext/config.py
start_flask/templates/ext/hooks.py
start_flask/templates/ext/migrate.py
start_flask/templates/ext/toolbar.py
start_flask/templates/ext/auth/__init__.py
start_flask/templates/ext/auth/admin.py
start_flask/templates/ext/auth/models.py
start_flask/templates/ext/db/__init__.py
start_flask/templates/ext/db/commands.py
start_flask/templates/ext/site/__init__.py
start_flask/templates/ext/site/main.py
start_flask/templates/templates/index.html