Metadata-Version: 2.1
Name: start-flask
Version: 0.1.11
Summary: Start a Flask project in a Application Factory Pattern
Home-page: https://github.com/cesargodoi/start_flask
Author: Cesar Godoi
Author-email: cesar.godoi@gmail.com
License: GNU GPLv3
Project-URL: source code, https://github.com/cesargodoi/start_flask
Platform: UNKNOWN
